Metadata-Version: 1.1
Name: jar-manifest
Version: 0.2
Summary: Returns the content of a jar file's MANIFEST as dict.
Home-page: http://github.com/nlohmann/jar_manifest
Author: Niels Lohmann
Author-email: mail@nlohmann.me
License: MIT
Keywords: jar file java manifest
Platform: UNKNOWN
Classifier: Development Status :: 4 - Beta
Classifier: License :: OSI Approved :: MIT License
Classifier: Programming Language :: Python :: 2.7
Classifier: Topic :: Software Development :: Libraries :: Java Libraries
